pyautogit/__init__.py
pyautogit/__main__.py
pyautogit/commands.py
pyautogit/errors.py
pyautogit/internal_editor_screen.py
pyautogit/logger.py
pyautogit/metadata_manager.py
pyautogit/repo_control_screen.py
pyautogit/repo_select_screen.py
pyautogit/screen_manager.py
pyautogit/settings_screen.py
pyautogit/askpass/__init__.py
pyautogit/askpass/askpass.py
pyautogit/askpass/askpass_win.py
pyautogit-0.0.5.dist-info/AUTHORS
pyautogit-0.0.5.dist-info/LICENSE
pyautogit-0.0.5.dist-info/METADATA
pyautogit-0.0.5.dist-info/WHEEL
pyautogit-0.0.5.dist-info/entry_points.txt
pyautogit-0.0.5.dist-info/top_level.txt
pyautogit-0.0.5.dist-info/RECORD
