Metadata-Version: 2.1
Name: pyautogit
Version: 0.0.5
Summary: A command line interface for working with git written in python with the help of py_cui.
Home-page: https://github.com/jwlodek/pyautogit
Author: Jakub Wlodek
Author-email: jwlodek.dev@gmail.com
License: BSD 3-Clause
Keywords: git command-line cli cui curses
Platform: UNKNOWN
Classifier: Development Status :: 3 - Alpha
Classifier: Intended Audience :: Developers
Classifier: Programming Language :: Python :: 3.4
Classifier: Programming Language :: Python :: 3.5
Classifier: Programming Language :: Python :: 3.6
Classifier: Programming Language :: Python :: 3.7
Classifier: Programming Language :: Python :: 3.8
Requires-Dist: py-cui (>=0.1.0)
Provides-Extra: test
Requires-Dist: pytest ; extra == 'test'
